{
  "wave": "w36",
  "base": "rolling-35-legacy-bridge-centralization-cumulative.zip",
  "deleted_wave_files": [
    "legacy_role_w04_aliases.php",
    "legacy_role_w05_aliases.php",
    "legacy_role_w06_aliases.php",
    "legacy_role_w07_aliases.php",
    "legacy_role_w08_aliases.php",
    "legacy_role_w09_aliases.php",
    "legacy_role_w10_aliases.php",
    "legacy_role_w11_aliases.php",
    "legacy_role_w12_aliases.php",
    "legacy_role_w13_aliases.php",
    "legacy_role_w14_aliases.php",
    "legacy_role_w16_aliases.php",
    "legacy_role_w17_aliases.php",
    "legacy_role_w18_aliases.php",
    "legacy_role_w19_aliases.php",
    "legacy_role_w23_aliases.php",
    "legacy_role_w26_aliases.php",
    "legacy_role_w27_aliases.php",
    "legacy_role_w28_aliases.php",
    "legacy_role_w35_aliases.php"
  ],
  "deleted_wave_file_count": 20,
  "consolidated_unique_aliases": 249,
  "new_file": "src/Legacy/Compatibility/legacy_role_w36_aliases.php"
}